qubitserving.cpython-311-x86_64-linux-gnu.so
qubitserving.pyi
qubitserving/lock/content.lock
qubitserving/lock/content.lock.enc
qubitserving-0.2.3.dist-info/METADATA
qubitserving-0.2.3.dist-info/WHEEL
qubitserving-0.2.3.dist-info/entry_points.txt
qubitserving-0.2.3.dist-info/top_level.txt
qubitserving-0.2.3.dist-info/zip-safe
qubitserving-0.2.3.dist-info/RECORD
qubitserving-0.2.3.dist-info/licenses/LICENSE
