Metadata-Version: 2.4
Name: qubitserving
Version: 0.2.3
Summary: Add your description here
Home-page: https://github.com/yaqiangsun/QubitServing.git
Author: Yaqiang Sun
Requires-Python: >=3.8
License-File: LICENSE
Requires-Dist: markupsafe>=3.0.3
Requires-Dist: modellock>=0.1.8
Requires-Dist: numpy>=2.3.4
Requires-Dist: opencv-python-headless>=4.11.0.86
Requires-Dist: python-multipart>=0.0.20
Requires-Dist: torch>=2.6.0
Requires-Dist: tqdm>=4.67.1
Requires-Dist: ultralytics>=8.3.221
Requires-Dist: uniserve>=0.0.5
Dynamic: author
Dynamic: home-page
Dynamic: license-file
Dynamic: requires-python
